.envrc
.gitlab-ci.yml
.pre-commit-config.yaml
AUTHORS
ChangeLog
LICENSE
MANIFEST.in
Makefile
Pipfile
Pipfile.lock
README.md
pytest.ini
setup.cfg
setup.py
tox.ini
docs/Makefile
docs/Pipfile
docs/Pipfile.lock
docs/conf.py
docs/hacking.rst
docs/index.rst
docs/release-notes.rst
docs/requirements.txt
fedeproxy/__init__.py
fedeproxy/cmd.py
fedeproxy/conftest.py
fedeproxy/django_middleware.py
fedeproxy/settings.py
fedeproxy/urls.py
fedeproxy/version.py
fedeproxy/wsgi.py
fedeproxy.egg-info/PKG-INFO
fedeproxy.egg-info/SOURCES.txt
fedeproxy.egg-info/dependency_links.txt
fedeproxy.egg-info/entry_points.txt
fedeproxy.egg-info/not-zip-safe
fedeproxy.egg-info/pbr.json
fedeproxy.egg-info/top_level.txt
fedeproxy/activitypub/__init__.py
fedeproxy/activitypub/base_activity.py
fedeproxy/activitypub/client.py
fedeproxy/activitypub/forgefed.py
fedeproxy/activitypub/person.py
fedeproxy/activitypub/regex.py
fedeproxy/activitypub/response.py
fedeproxy/activitypub/test_base_activity.py
fedeproxy/activitypub/test_client.py
fedeproxy/activitypub/verbs.py
fedeproxy/api/__init__.py
fedeproxy/api/admin.py
fedeproxy/api/apps.py
fedeproxy/api/models.py
fedeproxy/api/permissions.py
fedeproxy/api/views.py
fedeproxy/api/management/commands/fedeproxy_api.py
fedeproxy/api/migrations/__init__.py
fedeproxy/architecture/__init__.py
fedeproxy/architecture/dvcs/__init__.py
fedeproxy/architecture/dvcs/dvcs.py
fedeproxy/architecture/dvcs/git.py
fedeproxy/architecture/dvcs/hg.py
fedeproxy/architecture/dvcs/test_dvcs.py
fedeproxy/architecture/forge/__init__.py
fedeproxy/architecture/forge/forge.py
fedeproxy/architecture/forge/gitea.py
fedeproxy/architecture/forge/gitlab.py
fedeproxy/architecture/forge/test_forge.py
fedeproxy/architecture/forge/test_gitea.py
fedeproxy/architecture/forge/test_gitlab.py
fedeproxy/auth/__init__.py
fedeproxy/auth/apps.py
fedeproxy/cli/__init__.py
fedeproxy/cli/manage.py
fedeproxy/common/__init__.py
fedeproxy/common/retry.py
fedeproxy/common/test_retry.py
fedeproxy/domain/__init__.py
fedeproxy/domain/activitypub.py
fedeproxy/domain/fedeproxy.py
fedeproxy/domain/identity.py
fedeproxy/domain/test_fedeproxy.py
fedeproxy/domain/test_identity.py
fedeproxy/format/__init__.py
fedeproxy/format/format.py
